datasets/generic_monthly.json
datasets/generic_thresholds.json
datasets/monthly_thresholds.json
datasets/portfolio_data1.json
examples/python/calculate_thresholds.py
examples/python/calculate_variance.py
examples/python/conditional_migration_matrix.py
examples/python/loss_distributions.py
examples/python/portfolio_model.py
examples/python/validate_thresholds.py
examples/python/visualize_thresholds.py
portfolioAnalytics/__init__.py
portfolioAnalytics/creditmetrics.py
portfolioAnalytics/model.py
portfolioAnalytics/settings.py
portfolioAnalytics/vasicek.py
creditPortfolioAnalytics-0.4.dist-info/LICENSE
creditPortfolioAnalytics-0.4.dist-info/METADATA
creditPortfolioAnalytics-0.4.dist-info/WHEEL
creditPortfolioAnalytics-0.4.dist-info/top_level.txt
creditPortfolioAnalytics-0.4.dist-info/RECORD
