Metadata-Version: 2.1
Name: creditPortfolioAnalytics
Version: 0.4
Summary: A Python powered library for calculating semi-analytic credit portfolio loss metrics
Home-page: https://github.com/open-risk/portfolioAnalytics
Author: Open Risk
Author-email: info@openrisk.eu
License: UNKNOWN
Platform: UNKNOWN
Classifier: Intended Audience :: Developers
Classifier: Intended Audience :: Science/Research
Classifier: Intended Audience :: Financial and Insurance Industry
Classifier: Development Status :: 3 - Alpha
Classifier: License :: OSI Approved :: Apache Software License
Classifier: Operating System :: OS Independent
Classifier: Programming Language :: Python :: 3 :: Only
Classifier: Programming Language :: Python :: 3.7
Classifier: Topic :: Scientific/Engineering
Classifier: Topic :: Scientific/Engineering :: Information Analysis
Provides: portfolioAnalytics
License-File: LICENSE
Requires-Dist: pandas
Requires-Dist: numpy
Requires-Dist: scipy
Requires-Dist: statsmodels
Requires-Dist: sympy
Requires-Dist: matplotlib
